polars_darwin_core/__init__.py
polars_darwin_core/darwin_core.py
polars_darwin_core/dataframe.py
polars_darwin_core/lazyframe.py
polars_darwin_core/py.typed
polars_darwin_core-4.0.0.dist-info/METADATA
polars_darwin_core-4.0.0.dist-info/WHEEL
polars_darwin_core-4.0.0.dist-info/RECORD
