Metadata-Version: 2.4
Name: polars-darwin-core
Version: 4.0.0
Summary: Helpers for working with Darwin Core (DwC) CSVs using Polars.
Project-URL: Homepage, https://github.com/frewsxcv/polars-darwin-core
Author-email: Corey Farwell <coreyf@rwell.org>
License-Expression: Apache-2.0 OR MIT
Keywords: biodiversity,csv,darwin-core,gbif,polars
Classifier: License :: OSI Approved :: MIT License
Classifier: Operating System :: OS Independent
Classifier: Programming Language :: Python :: 3
Requires-Python: >=3.10
Requires-Dist: polars>=0.30
